{
  "db_name": "PostgreSQL",
  "query": "UPDATE as_client_record SET\n                    activity_time = $1,\n                    credential = $2,\n                    remaining_tokens = $3\n                WHERE user_uuid = $4 AND user_domain = $5",
  "describe": {
    "columns": [],
    "parameters": {
      "Left": [
        "Timestamptz",
        {
          "Custom": {
            "name": "client_credential",
            "kind": {
              "Composite": [
                [
                  "version",
                  "Bytea"
                ],
                [
                  "signature_scheme",
                  "Bytea"
                ],
                [
                  "verifying_key",
                  "Bytea"
                ],
                [
                  "expiration_data",
                  {
                    "Custom": {
                      "name": "expiration",
                      "kind": {
                        "Composite": [
                          [
                            "not_before",
                            "Timestamptz"
                          ],
                          [
                            "not_after",
                            "Timestamptz"
                          ]
                        ]
                      }
                    }
                  }
                ],
                [
                  "signer_fingerprint",
                  "Bytea"
                ],
                [
                  "signature",
                  "Bytea"
                ]
              ]
            }
          }
        },
        "Int4",
        "Uuid",
        "Text"
      ]
    },
    "nullable": []
  },
  "hash": "deab70299a430116662035343b9a9eaea459fc144f75c2293ca2ce08647dff8b"
}
