{
  "db_name": "SQLite",
  "query": "INSERT INTO conversation_messages (\n                message_id,\n                conversation_id,\n                timestamp,\n                sender_as_client_uuid,\n                sender_as_domain,\n                content,\n                sent\n            ) VALUES (?, ?, ?, ?, ?, ?, ?)",
  "describe": {
    "columns": [],
    "parameters": {
      "Right": 7
    },
    "nullable": []
  },
  "hash": "1a5e2cbb823820c65502b1aae3c85c7bf07ede8a554e45e15e6c5cd40cdeefb4"
}
