{
  "db_name": "SQLite",
  "query": "SELECT\n                verifying_key,\n                leaf_signing_key AS \"leaf_signing_key: _\",\n                identity_link_key AS \"identity_link_key: _\"\n            FROM leaf_keys WHERE verifying_key = ?",
  "describe": {
    "columns": [
      {
        "name": "verifying_key",
        "ordinal": 0,
        "type_info": "Blob"
      },
      {
        "name": "leaf_signing_key: _",
        "ordinal": 1,
        "type_info": "Blob"
      },
      {
        "name": "identity_link_key: _",
        "ordinal": 2,
        "type_info": "Blob"
      }
    ],
    "parameters": {
      "Right": 1
    },
    "nullable": [
      false,
      false,
      false
    ]
  },
  "hash": "83f210e4c50b47f2dbd3ff4b5d2f55bbcbcb9a0743cbe1ecbcbfea71c6d065df"
}
